GUTOOLS/__init__.py
GUTOOLS/tools.py
GUTOOLS/util.py
GUToolsP-0.1.5.dist-info/METADATA
GUToolsP-0.1.5.dist-info/WHEEL
GUToolsP-0.1.5.dist-info/top_level.txt
GUToolsP-0.1.5.dist-info/RECORD
