Metadata-Version: 2.1
Name: GUToolsP
Version: 0.1.5
Summary: GUToolsP
Home-page: http://autozone-prod.pin-dao.cn
Author: TM-QA-Gu
Author-email: guhao@pin-dao.cn
License: MIT
Platform: UNKNOWN
Classifier: License :: OSI Approved :: MIT License
Classifier: Programming Language :: Python
Classifier: Programming Language :: Python :: 3
Requires-Python: >=3.6.8
Requires-Dist: yagmail
